BlockChainExplorer/BlockChainExplorer.py
BlockChainExplorer/__init__.py
BlockChainExplorer-0.0.3.dist-info/LICENSE.txt
BlockChainExplorer-0.0.3.dist-info/METADATA
BlockChainExplorer-0.0.3.dist-info/WHEEL
BlockChainExplorer-0.0.3.dist-info/top_level.txt
BlockChainExplorer-0.0.3.dist-info/RECORD
