Metadata-Version: 2.1
Name: BlockChainExplorer
Version: 0.0.3
Summary: Simple package to access EVM blockchain explorers, currently supports Binance Smart Chain, Ethereum, Avalanche and Polygon
Author-email: ManiacalEngineer <unhfireboy@yahoo.com>
License: MIT License
Project-URL: Homepage, https://github.com/ManicalEngineer/BlockChainExplorer
Classifier: Programming Language :: Python :: 3
Classifier: License :: OSI Approved :: MIT License
Classifier: Operating System :: OS Independent
Requires-Python: >=3.7
License-File: LICENSE.txt
Requires-Dist: Requests (==2.31.0)
